gator/_vendor/__init__.py
gator/_vendor/marshmallow_mongoengine/__init__.py
src/gator/_vendor/marshmallow_mongoengine/__pycache__/__init__.cpython-311.pyc
src/gator/_vendor/marshmallow_mongoengine/__pycache__/convert.cpython-311.pyc
src/gator/_vendor/marshmallow_mongoengine/__pycache__/exceptions.cpython-311.pyc
src/gator/_vendor/marshmallow_mongoengine/__pycache__/fields.cpython-311.pyc
src/gator/_vendor/marshmallow_mongoengine/__pycache__/schema.cpython-311.pyc
gator/_vendor/marshmallow_mongoengine/conversion/__init__.py
src/gator/_vendor/marshmallow_mongoengine/conversion/__pycache__/__init__.cpython-311.pyc
src/gator/_vendor/marshmallow_mongoengine/conversion/__pycache__/fields.cpython-311.pyc
src/gator/_vendor/marshmallow_mongoengine/conversion/__pycache__/params.cpython-311.pyc
gator/_vendor/marshmallow_mongoengine/conversion/fields.py
gator/_vendor/marshmallow_mongoengine/conversion/params.py
gator/_vendor/marshmallow_mongoengine/convert.py
gator/_vendor/marshmallow_mongoengine/exceptions.py
gator/_vendor/marshmallow_mongoengine/fields.py
gator/_vendor/marshmallow_mongoengine/schema.py
gator/_vendor/marshmallow_mongoengine-0.31.1.dist-info/INSTALLER
gator/_vendor/marshmallow_mongoengine-0.31.1.dist-info/LICENSE
gator/_vendor/marshmallow_mongoengine-0.31.1.dist-info/METADATA
gator/_vendor/marshmallow_mongoengine-0.31.1.dist-info/RECORD
gator/_vendor/marshmallow_mongoengine-0.31.1.dist-info/REQUESTED
gator/_vendor/marshmallow_mongoengine-0.31.1.dist-info/WHEEL
gator/_vendor/marshmallow_mongoengine-0.31.1.dist-info/direct_url.json
gator/_vendor/marshmallow_mongoengine-0.31.1.dist-info/top_level.txt
gator/core/data/dataset.py
gator/core/data/utils/__init__.py
gator/core/data/utils/hash.py
gator/core/data/utils/io.py
gator/core/data/utils/serialization.py
gator/core/models/__init__.py
gator/core/models/common.py
gator/core/models/institution.py
gator/core/models/mongoengine_typing.py
gator/core/models/timetable.py
gator/core/schemas/__init__.py
gator/core/schemas/institution.py
gator/core/schemas/timetable.py
gator_core-2.0.0.dist-info/LICENSE
gator_core-2.0.0.dist-info/METADATA
gator_core-2.0.0.dist-info/WHEEL
gator_core-2.0.0.dist-info/RECORD
